README.txt
setup.cfg
setup.py
EatLint.egg-info/PKG-INFO
EatLint.egg-info/SOURCES.txt
EatLint.egg-info/dependency_links.txt
EatLint.egg-info/entry_points.txt
EatLint.egg-info/not-zip-safe
EatLint.egg-info/top_level.txt
eatlint/__init__.py
eatlint/lint.py