Metadata-Version: 1.0
Name: EatLint
Version: 1.1.0
Summary: PyLint Summary and Graph Generators for Bitten.
Home-page: https://echospiral.com/trac/eatlint
Author: Jeffrey Kyllo
Author-email: jkyllo-eatlint@echospiral.com
License: UNKNOWN
Keywords: trac,bitten,lint,pylint
Platform: UNKNOWN
Classifier: Programming Language :: Python
Classifier: Operating System :: OS Independent
Classifier: License :: OSI Approved :: BSD License
Classifier: Natural Language :: English
